[
  {
    "i": "vici:vici-24643",
    "la": 34.5549,
    "lo": 38.2739,
    "k": "camp",
    "p": "v",
    "n": "Barraks, Palmyra",
    "t": 2
  },
  {
    "i": "vici:vici-26276",
    "la": 42.5475,
    "lo": 26.4837,
    "k": "camp",
    "p": "v",
    "n": "Kabyle",
    "e": 1500,
    "t": 2
  },
  {
    "i": "vici:vici-28749",
    "la": 50.7814,
    "lo": 5.4674,
    "k": "camp",
    "p": "v",
    "n": "Tongeren - Kielenstraat",
    "t": 2
  },
  {
    "i": "vici:vici-33546",
    "la": 48.2114,
    "lo": 16.3708,
    "k": "camp",
    "p": "v",
    "n": "Kommandatur Legionslager Vindobona",
    "s": 97,
    "t": 2
  },
  {
    "i": "vici:vici-58533",
    "la": 41.8549,
    "lo": 12.5461,
    "k": "camp",
    "p": "v",
    "n": "Vitiges Camp",
    "s": 537,
    "t": 2
  },
  {
    "i": "vici:vici-66559",
    "la": 49.084,
    "lo": -0.3541,
    "k": "camp",
    "p": "v",
    "n": "Camp",
    "s": 10,
    "t": 2
  },
  {
    "i": "vici:vici-82702",
    "la": 44.2717,
    "lo": 28.1789,
    "k": "camp",
    "p": "v",
    "n": "Roman camp ?",
    "e": 1500,
    "t": 2
  },
  {
    "i": "vici:vici-83885",
    "la": 44.1196,
    "lo": 24.9551,
    "k": "camp",
    "p": "v",
    "n": "Gresia",
    "e": 1500,
    "t": 2
  }
]
