[
  {
    "i": "vici:vici-26276",
    "la": 42.5475,
    "lo": 26.4837,
    "k": "camp",
    "p": "v",
    "n": "Kabyle",
    "e": 1500,
    "t": 2
  },
  {
    "i": "vici:vici-28749",
    "la": 50.7814,
    "lo": 5.4674,
    "k": "camp",
    "p": "v",
    "n": "Tongeren - Kielenstraat",
    "t": 2
  },
  {
    "i": "vici:vici-33546",
    "la": 48.2114,
    "lo": 16.3708,
    "k": "camp",
    "p": "v",
    "n": "Kommandatur Legionslager Vindobona",
    "s": 97,
    "t": 2
  },
  {
    "i": "vici:vici-58533",
    "la": 41.8549,
    "lo": 12.5461,
    "k": "camp",
    "p": "v",
    "n": "Vitiges Camp",
    "s": 537,
    "t": 2
  }
]
